openshift_cluster_login/__init__.py
openshift_cluster_login/__main__.py
openshift_cluster_login/ui.py
openshift_cluster_login/gql_definitions/__init__.py
openshift_cluster_login/gql_definitions/clusters.gql
openshift_cluster_login/gql_definitions/clusters.py
openshift_cluster_login/gql_definitions/namespaces.gql
openshift_cluster_login/gql_definitions/namespaces.py
openshift_cluster_login/gql_definitions/fragments/__init__.py
openshift_cluster_login/gql_definitions/fragments/cluster.gql
openshift_cluster_login/gql_definitions/fragments/cluster.py
openshift_cluster_login-1.4.0.dist-info/METADATA
openshift_cluster_login-1.4.0.dist-info/WHEEL
openshift_cluster_login-1.4.0.dist-info/entry_points.txt
openshift_cluster_login-1.4.0.dist-info/licenses/LICENSE
openshift_cluster_login-1.4.0.dist-info/RECORD
