Metadata-Version: 2.4
Name: openshift-cluster-login
Version: 1.4.0
Summary: Openshift cluster login on command line
Project-URL: homepage, http://github.com/chassing/ocl
Project-URL: respository, http://github.com/chassing/ocl
Project-URL: issues, http://github.com/chassing/ocl/issues
Author-email: Christian Assing <chris@ca-net.org>
License: MIT License
License-File: LICENSE
Classifier: Development Status :: 5 - Production/Stable
Classifier: Environment :: Console
Classifier: License :: OSI Approved :: MIT License
Classifier: Operating System :: MacOS :: MacOS X
Classifier: Operating System :: POSIX :: Linux
Classifier: Programming Language :: Python :: 3.11
Classifier: Programming Language :: Python :: 3.12
Classifier: Programming Language :: Python :: 3.13
Classifier: Topic :: Software Development :: Build Tools
Classifier: Topic :: Software Development :: Libraries :: Python Modules
Classifier: Topic :: System :: System Shells
Classifier: Topic :: System :: Systems Administration
Classifier: Topic :: Terminals :: Terminal Emulators/X Terminals
Requires-Python: >=3.11
Requires-Dist: appdirs>=1.4.4
Requires-Dist: diskcache>=5.6.3
Requires-Dist: flufl-lock>=8.1.0
Requires-Dist: fuzzyfinder>=2.3.0
Requires-Dist: pydantic>=2.8.2
Requires-Dist: pyquery>=2.0.0
Requires-Dist: requests-gssapi>=1.4.0
Requires-Dist: requests>=2.32.3
Requires-Dist: rich>=13.7.1
Requires-Dist: textual>=5.3.0
Requires-Dist: typer>=0.12.5
